genopen/__init__.py
genopen/cli.py
genopen/commands/__init__.py
genopen/commands/add.py
genopen/commands/build.py
genopen/commands/create.py
genopen/template/genopen.config
genopen/template/themes/default/404.html
genopen/template/themes/default/index.html
genopen/template/themes/default/index.post.html
genopen/template/themes/default/post.html
genopen/template/themes/default/robots.txt
genopen/template/themes/default/assets/404.jpg
genopen/template/themes/default/assets/empty.png
genopen/template/themes/default/css/style.css
genopen/template/themes/default/js/pagination.js
genopen-1.1.0.dist-info/LICENSE
genopen-1.1.0.dist-info/METADATA
genopen-1.1.0.dist-info/WHEEL
genopen-1.1.0.dist-info/entry_points.txt
genopen-1.1.0.dist-info/top_level.txt
genopen-1.1.0.dist-info/RECORD
