Metadata-Version: 2.1
Name: genopen
Version: 1.1.0
Summary: Markdown to blog generator
Home-page: https://github.com/MathieuBourgois/genopen/
Author: Mathieu Bourgois
Author-email: bourgois.mathieu+genopen@gmail.com
Classifier: Programming Language :: Python :: 3
Classifier: License :: OSI Approved :: MIT License
Classifier: Operating System :: OS Independent
License-File: LICENSE
Requires-Dist: click==8.1.7
Requires-Dist: Markdown==3.7
Requires-Dist: PyYAML==6.0.2
